imath/__init__.py
imath/rch.py
imath-0.0.2.dist-info/METADATA
imath-0.0.2.dist-info/WHEEL
imath-0.0.2.dist-info/top_level.txt
imath-0.0.2.dist-info/RECORD
