Metadata-Version: 2.1
Name: imath
Version: 0.0.2
Summary: innovata-debug
Home-page: https://github.com/innovata/imath
Author: innovata sambong
Author-email: iinnovata@gmail.com
License: UNKNOWN
Platform: UNKNOWN
Classifier: Programming Language :: Python :: 3
Classifier: License :: OSI Approved :: MIT License
Classifier: Operating System :: OS Independent
Requires-Python: >=3.8
